ppc/__init__.py
ppc/clusterized_dataframe.py
ppc/protein_dataframe.py
ppc/enums/clusters.py
ppc/enums/columns.py
ppc/enums/super_kingdom.py
ppc/helpers/pandas_helper.py
ppc/helpers/printer_helper.py
prot_pipeline_creator-1.0.1.dist-info/licenses/LICENSE
prot_pipeline_creator-1.0.1.dist-info/METADATA
prot_pipeline_creator-1.0.1.dist-info/WHEEL
prot_pipeline_creator-1.0.1.dist-info/top_level.txt
prot_pipeline_creator-1.0.1.dist-info/RECORD
