Metadata-Version: 2.4
Name: prot-pipeline-creator
Version: 1.0.1
Summary: A tool for creating protein analysis pipelines for UniProt.
Author-email: Emanuel Umbelino <umbelino.emanuel@gmail.com>
License:                                  Apache License
Project-URL: Homepage, https://github.com/emanuelumbelino/prot-pipeline-creator
Project-URL: Bug Tracker, https://github.com/emanuelumbelino/prot-pipeline-creator/issues
Classifier: Programming Language :: Python :: 3
Classifier: License :: OSI Approved :: Apache Software License
Classifier: Operating System :: OS Independent
Requires-Python: >=3.8
License-File: LICENSE
Requires-Dist: pandas
Dynamic: license-file
